noisecut/max_cut/__init__.py
noisecut/max_cut/base_maxcut.py
noisecut/max_cut/solvers.py
noisecut/model/__init__.py
noisecut/model/noisecut_coder.py
noisecut/model/noisecut_model.py
noisecut/tree_structured/__init__.py
noisecut/tree_structured/base.py
noisecut/tree_structured/base_structured_data.py
noisecut/tree_structured/binary_function.py
noisecut/tree_structured/data_manipulator.py
noisecut/tree_structured/sample_generator.py
noisecut/tree_structured/structured_data.py
noisecut-0.2.1.dist-info/LICENSE
noisecut-0.2.1.dist-info/METADATA
noisecut-0.2.1.dist-info/WHEEL
noisecut-0.2.1.dist-info/RECORD
