Metadata-Version: 2.1
Name: noisecut
Version: 0.2.1
Summary: A Python Package for Noise-Tolerant Classification of Binary Data using Prior Knowledge Integration and Max-Cut Solutions
Home-page: https://github.com/JRC-COMBINE/NoiseCut
Author: Hedieh Mirzaieazar, Moein E. Samadi
Author-email: moein.samadi@rwth-aachen.de
Requires-Python: >=3.9,<4.0
Classifier: Development Status :: 3 - Alpha
Classifier: Intended Audience :: Science/Research
Classifier: License :: OSI Approved :: GNU General Public License v3 (GPLv3)
Classifier: Operating System :: MacOS
Classifier: Operating System :: Microsoft :: Windows
Classifier: Operating System :: POSIX :: Linux
Classifier: Programming Language :: Python :: 3
Classifier: Programming Language :: Python :: 3.9
Classifier: Programming Language :: Python :: 3.10
Classifier: Programming Language :: Python :: 3.11
Classifier: Programming Language :: Python :: 3.10
Classifier: Programming Language :: Python :: 3.11
Classifier: Programming Language :: Python :: 3.9
Classifier: Topic :: Scientific/Engineering
Requires-Dist: cplex
Requires-Dist: docplex
Requires-Dist: numpy
Requires-Dist: pandas
Requires-Dist: scipy
Project-URL: Documentation, https://noisecut.readthedocs.io/en/latest/
Project-URL: Repository, https://github.com/JRC-COMBINE/NoiseCut
